YahooFinanceDashboard/__init__.py
YahooFinanceDashboard/data_io.py
YahooFinanceDashboard/filter_data.py
YahooFinanceDashboard/plots.py
YahooFinanceDashboard/_data_io/YahooTickerDownloader.py
YahooFinanceDashboard/_data_io/__init__.py
YahooFinanceDashboard/_data_io/_helpers.py
YahooFinanceDashboard/_data_io/database_manager.py
YahooFinanceDashboard/_data_io/difflib.py
YahooFinanceDashboard/_data_io/yahoo_interface.py
YahooFinanceDashboard/_data_io/_dbs/__dummy.sqlite
YahooFinanceDashboard/_data_io/_dbs/__readme.txt
YahooFinanceDashboard/_data_io/_dbs/__yahoo_tickers/__last_update.log
YahooFinanceDashboard/_data_io/_dbs/__yahoo_tickers/generic.pickle
YahooFinanceDashboard/_data_io/_dbs/__yahoo_tickers/generic.sqlite
YahooFinanceDashboard/_plots/__init__.py
YahooFinanceDashboard/_plots/_plots_axes.py
YahooFinanceDashboard-1.1.86.dist-info/LICENSE.txt
YahooFinanceDashboard-1.1.86.dist-info/METADATA
YahooFinanceDashboard-1.1.86.dist-info/WHEEL
YahooFinanceDashboard-1.1.86.dist-info/top_level.txt
YahooFinanceDashboard-1.1.86.dist-info/RECORD
